LICENSE
MANIFEST.in
README.rst
requirements.txt
setup.py
djangocms_votes.egg-info/PKG-INFO
djangocms_votes.egg-info/SOURCES.txt
djangocms_votes.egg-info/dependency_links.txt
djangocms_votes.egg-info/not-zip-safe
djangocms_votes.egg-info/requires.txt
djangocms_votes.egg-info/top_level.txt
djcms_votes/__init__.py
djcms_votes/admin.py
djcms_votes/app_urls.py
djcms_votes/appviews.py
djcms_votes/cms_apps.py
djcms_votes/forms.py
djcms_votes/lookups.py
djcms_votes/mail.py
djcms_votes/models.py
djcms_votes/requirements_urls.py
djcms_votes/tests.py
djcms_votes/urls.py
djcms_votes/utils.py
djcms_votes/views.py
djcms_votes/bucket/__init__.py
djcms_votes/bucket/basic_bucket.py
djcms_votes/bucket/views.py
djcms_votes/locale/es/LC_MESSAGES/django.mo
djcms_votes/locale/es/LC_MESSAGES/django.po
djcms_votes/migrations/0001_initial.py
djcms_votes/migrations/0002_poll.py
djcms_votes/migrations/0003_auto_20160926_2309.py
djcms_votes/migrations/__init__.py
djcms_votes/static/css/bootstrap-datepicker.css
djcms_votes/static/css/djcms_votes.css
djcms_votes/static/js/Chart.2_2_2.min.js
djcms_votes/static/js/Chart.bundle.2_2_2.min.js
djcms_votes/static/js/bootstrap-datepicker.js
djcms_votes/static/js/djcms_votes.js
djcms_votes/templates/djcms_votes/comment_chart.html
djcms_votes/templates/djcms_votes/comment_form.html
djcms_votes/templates/djcms_votes/comment_list.html
djcms_votes/templates/djcms_votes/comments_display.html
djcms_votes/templates/djcms_votes/facebook_btn.html
djcms_votes/templates/djcms_votes/likes.html
djcms_votes/templates/djcms_votes/login.html
djcms_votes/templates/djcms_votes/pagination.html
djcms_votes/templates/djcms_votes/poll_chart.html
djcms_votes/templates/djcms_votes/poll_likes.html
djcms_votes/templates/djcms_votes/user_comment_chart.html
djcms_votes/templates/djcms_votes/user_poll_chart.html
djcms_votes/templates/djcms_votes/user_votes.html
djcms_votes/templates/djcms_votes/app/bucket.html
djcms_votes/templates/djcms_votes/app/graph.html
djcms_votes/templates/djcms_votes/mail/comment.html
djcms_votes/templatetags/__init__.py
djcms_votes/templatetags/user_votes.py
djcms_votes/templatetags/votes.py