Metadata-Version: 1.1
Name: djangocms-votes
Version: 0.1.2
Summary: Django cms comments, and rate system with stats.
Home-page: https://github.com/luisza/djangocms-votes
Author: Luis Zarate
Author-email: luis.zarate@solvosoft.com
License: GNU General Public License v3 (GPLv3)
Platform: OS Independent
Classifier: Environment :: Web Environment
Classifier: Framework :: Django
Classifier: Framework :: Django :: 1.8
Classifier: Framework :: Django :: 1.9
Classifier: Intended Audience :: Developers
Classifier: License :: OSI Approved :: GNU General Public License v3 (GPLv3)
Classifier: Operating System :: OS Independent
Classifier: Programming Language :: Python
Classifier: Programming Language :: Python :: 3.5
Classifier: Topic :: Internet :: WWW/HTTP
Classifier: Topic :: Internet :: WWW/HTTP :: Dynamic Content
Classifier: Topic :: Software Development :: Libraries :: Python Modules
Classifier: Development Status :: 4 - Beta
